pydicom/__init__.py
pydicom/_dicom_dict.py
pydicom/_private_dict.py
pydicom/_storage_sopclass_uids.py
pydicom/_uid_dict.py
pydicom/_version.py
pydicom/charset.py
pydicom/compat.py
pydicom/config.py
pydicom/datadict.py
pydicom/dataelem.py
pydicom/dataset.py
pydicom/dicomdir.py
pydicom/dicomio.py
pydicom/encaps.py
pydicom/env_info.py
pydicom/errors.py
pydicom/filebase.py
pydicom/filereader.py
pydicom/fileset.py
pydicom/fileutil.py
pydicom/filewriter.py
pydicom/jsonrep.py
pydicom/misc.py
pydicom/multival.py
pydicom/py.typed
pydicom/sequence.py
pydicom/tag.py
pydicom/uid.py
pydicom/valuerep.py
pydicom/values.py
pydicom/cli/__init__.py
pydicom/cli/codify.py
pydicom/cli/main.py
pydicom/cli/show.py
pydicom/data/__init__.py
pydicom/data/data_manager.py
pydicom/data/download.py
pydicom/data/hashes.json
pydicom/data/retry.py
pydicom/data/urls.json
pydicom/data/charset_files/FileInfo.txt
pydicom/data/charset_files/chrArab.dcm
pydicom/data/charset_files/chrFren.dcm
pydicom/data/charset_files/chrFrenMulti.dcm
pydicom/data/charset_files/chrGerm.dcm
pydicom/data/charset_files/chrGreek.dcm
pydicom/data/charset_files/chrH31.dcm
pydicom/data/charset_files/chrH32.dcm
pydicom/data/charset_files/chrHbrw.dcm
pydicom/data/charset_files/chrI2.dcm
pydicom/data/charset_files/chrJapMulti.dcm
pydicom/data/charset_files/chrJapMultiExplicitIR6.dcm
pydicom/data/charset_files/chrKoreanMulti.dcm
pydicom/data/charset_files/chrRuss.dcm
pydicom/data/charset_files/chrSQEncoding.dcm
pydicom/data/charset_files/chrSQEncoding1.dcm
pydicom/data/charset_files/chrX1.dcm
pydicom/data/charset_files/chrX2.dcm
pydicom/data/palettes/README.md
pydicom/data/palettes/fall.dcm
pydicom/data/palettes/hotiron.dcm
pydicom/data/palettes/hotmetalblue.dcm
pydicom/data/palettes/pet.dcm
pydicom/data/palettes/pet20step.dcm
pydicom/data/palettes/spring.dcm
pydicom/data/palettes/summer.dcm
pydicom/data/palettes/winter.dcm
pydicom/data/test_files/693_J2KI.dcm
pydicom/data/test_files/CT_small.dcm
pydicom-2.4.0.dist-info/entry_points.txt
pydicom-2.4.0.dist-info/LICENSE
pydicom-2.4.0.dist-info/WHEEL
pydicom-2.4.0.dist-info/METADATA
pydicom-2.4.0.dist-info/RECORD
