Metadata-Version: 2.1
Name: pydicom
Version: 2.4.0
Summary: A pure Python package for reading and writing DICOM data
Keywords: dicom, python, medical, imaging
Author-email: Darcy Mason and contributors <darcymason@gmail.com>
Requires-Python: >=3.7
Classifier: License :: OSI Approved :: MIT License
Classifier: Intended Audience :: Developers
Classifier: Intended Audience :: Healthcare Industry
Classifier: Intended Audience :: Science/Research
Classifier: Development Status :: 5 - Production/Stable
Classifier: Programming Language :: Python
Classifier: Programming Language :: Python :: 3.7
Classifier: Programming Language :: Python :: 3.8
Classifier: Programming Language :: Python :: 3.9
Classifier: Programming Language :: Python :: 3.10
Classifier: Programming Language :: Python :: 3.11
Classifier: Operating System :: OS Independent
Classifier: Topic :: Scientific/Engineering :: Medical Science Apps.
Classifier: Topic :: Scientific/Engineering :: Physics
Classifier: Topic :: Software Development :: Libraries
Requires-Dist: numpy ; extra == "docs"
Requires-Dist: numpydoc ; extra == "docs"
Requires-Dist: matplotlib ; extra == "docs"
Requires-Dist: pillow ; extra == "docs"
Requires-Dist: sphinx ; extra == "docs"
Requires-Dist: sphinx_rtd_theme ; extra == "docs"
Requires-Dist: sphinx-gallery ; extra == "docs"
Requires-Dist: sphinxcontrib-napoleon ; extra == "docs"
Requires-Dist: sphinx-copybutton ; extra == "docs"
Project-URL: documentation, https://pydicom.github.io/pydicom
Project-URL: download, https://github.com/pydicom/pydicom/archive/master.zip
Project-URL: homepage, https://github.com/pydicom/pydicom
Project-URL: repository, https://github.com/pydicom/pydicom
Provides-Extra: docs
